mercury_parser.py
mercury_parser-0.1.2.dist-info/DESCRIPTION.rst
mercury_parser-0.1.2.dist-info/METADATA
mercury_parser-0.1.2.dist-info/RECORD
mercury_parser-0.1.2.dist-info/WHEEL
mercury_parser-0.1.2.dist-info/metadata.json
mercury_parser-0.1.2.dist-info/top_level.txt
