Metadata-Version: 2.0
Name: mercury-parser
Version: 0.1.2
Summary: Mercury Web Parser API Client.
Home-page: https://github.com/kennethreitz/mercury-parser
Author: Kenneth Reitz
Author-email: me@kennethreitz.com
License: MIT
Platform: UNKNOWN
Requires-Dist: maya
Requires-Dist: requests
